cuery/__init__.py
cuery/asy.py
cuery/call.py
cuery/cli.py
cuery/context.py
cuery/cost.py
cuery/models.py
cuery/pretty.py
cuery/prompt.py
cuery/response.py
cuery/search.py
cuery/task.py
cuery/tool.py
cuery/utils.py
cuery/actors/__init__.py
cuery/actors/assign_topic.py
cuery/actors/automagic.py
cuery/actors/brands.py
cuery/actors/classify.py
cuery/actors/entities.py
cuery/actors/funnel.py
cuery/actors/geo.py
cuery/actors/keyword_ideas.py
cuery/actors/keyword_metrics.py
cuery/actors/score.py
cuery/actors/serps.py
cuery/actors/topics.py
cuery/actors/utils.py
cuery/actors/scaffold/__init__.py
cuery/actors/scaffold/flex.py
cuery/actors/scaffold/stubs.py
cuery/builder/__init__.py
cuery/builder/chat.py
cuery/builder/ui.py
cuery/resources/__init__.py
cuery/resources/google_ads_countries.csv
cuery/resources/google_ads_langs.csv
cuery/resources/google_country_coords.csv
cuery/seo/__init__.py
cuery/seo/autocomplete.py
cuery/seo/brands.py
cuery/seo/funnels.py
cuery/seo/geo.py
cuery/seo/keywords.py
cuery/seo/seo.py
cuery/seo/serps.py
cuery/seo/sources.py
cuery/seo/tools.py
cuery/seo/traffic.py
cuery/seo/aio/__init__.py
cuery/seo/aio/apify.py
cuery/seo/aio/hasdata.py
cuery/seo/aio/scrapingdog.py
cuery/server/__init__.py
cuery/server/server.py
cuery/templates/__init__.py
cuery/templates/record_to_json.jinja
cuery/templates/record_to_md.jinja
cuery/templates/record_to_text.jinja
cuery/templates/records_attr_wise.jinja
cuery/templates/records_rec_wise.jinja
cuery/tools/__init__.py
cuery/tools/abs.py
cuery/tools/schema.py
cuery/tools/topics.py
cuery/tools/flex/__init__.py
cuery/tools/flex/base.py
cuery/tools/flex/classify.py
cuery/tools/flex/entities.py
cuery/tools/flex/generic.py
cuery/tools/flex/score.py
cuery/tools/flex/topics.py
cuery-0.33.2.dist-info/METADATA
cuery-0.33.2.dist-info/WHEEL
cuery-0.33.2.dist-info/entry_points.txt
cuery-0.33.2.dist-info/licenses/LICENSE
cuery-0.33.2.dist-info/RECORD
