Metadata-Version: 2.4
Name: cuery
Version: 0.33.2
Summary: Prompt (cue) management and execution for tabular data.
Project-URL: Homepage, https://github.com/graphext/cuery
Project-URL: Documentation, https://cuery.readthedocs.io/
Author-email: Thomas Buhrmann <thomas@graphext.com>
License-Expression: Apache-2.0
License-File: LICENSE
Keywords: ai,data analysis,data processing,data science,llm,prompt engineering,prompt management,structured output,tabular data
Classifier: Development Status :: 4 - Beta
Classifier: Intended Audience :: Developers
Classifier: License :: OSI Approved :: Apache Software License
Classifier: Programming Language :: Python :: 3
Classifier: Topic :: Scientific/Engineering
Classifier: Topic :: Software Development :: Libraries
Classifier: Topic :: Software Development :: Libraries :: Python Modules
Requires-Python: >=3.10
Requires-Dist: aiohttp>=3.9.0
Requires-Dist: async-lru>=2.0.5
Requires-Dist: datamodel-code-generator>=0.32.0
Requires-Dist: fastapi-mcp>=0.3.4
Requires-Dist: fastapi>=0.115.12
Requires-Dist: glom>=24.11.0
Requires-Dist: google-genai>=1.56.0
Requires-Dist: instructor[anthropic,google-genai]>=1.13.0
Requires-Dist: jsonschema>=4.17.0
Requires-Dist: levenshtein>=0.27.1
Requires-Dist: litellm<=1.77.1,>=1.69.1
Requires-Dist: markdown>=3.9
Requires-Dist: openai>=1.109
Requires-Dist: pandas>=2.2.3
Requires-Dist: pre-commit
Requires-Dist: pyarrow>=20.0.0
Requires-Dist: pydantic[email]>=2.0.0
Requires-Dist: python-dotenv>=1.1.0
Requires-Dist: pyyaml>=6.0.2
Requires-Dist: rich>=13.9.4
Requires-Dist: tenacity
Requires-Dist: tiktoken>=0.9.0
Requires-Dist: tldextract>=5.3.0
Requires-Dist: typer>=0.15.4
Requires-Dist: uvicorn>=0.34.3
Requires-Dist: xai-sdk<2.0.0,>=1.1.0
Provides-Extra: seo
Requires-Dist: apify; extra == 'seo'
Requires-Dist: google-ads<28.0.0; extra == 'seo'
Requires-Dist: gradio>=5.9.1; extra == 'seo'
Requires-Dist: matplotlib; extra == 'seo'
Requires-Dist: plotly[express]>=6.3.0; extra == 'seo'
